LICENSE
MANIFEST.in
README.md
requirements.txt
setup.py
version.properties
testsinyaml/__init__.py
testsinyaml/parser.py
testsinyaml/select_executers.py
testsinyaml/test.py
testsinyaml.egg-info/PKG-INFO
testsinyaml.egg-info/SOURCES.txt
testsinyaml.egg-info/dependency_links.txt
testsinyaml.egg-info/requires.txt
testsinyaml.egg-info/top_level.txt
testsinyaml/executers/__init__.py
testsinyaml/executers/command_executer.py
testsinyaml/executers/http_executer.py
testsinyaml/executers/telnet_executer.py