Metadata-Version: 2.1
Name: testsinyaml
Version: 0.1.0
Summary: testsinyaml: Define your test cases in YAML and they will get executed and the result will be shared. 
Home-page: https://github.com/chowmean/testsinyaml
Author: chowmean
Author-email: gaurav.dev.iiitm@gmail.com
License: Apache-2.0
Keywords: python,tests,test_automation
Platform: UNKNOWN
Classifier: Programming Language :: Python
Classifier: Operating System :: OS Independent
Classifier: Intended Audience :: Developers
Classifier: Development Status :: 4 - Beta
Classifier: Environment :: Plugins
Classifier: Topic :: Software Development :: Testing
Classifier: License :: OSI Approved :: Apache Software License
Classifier: Natural Language :: English
